drb/drivers/http/__init__.py
drb/drivers/http/_version.py
drb/drivers/http/http.py
drb/drivers/http/oauth2/HTTPOAuth2.py
drb/drivers/http/oauth2/__init__.py
drb/drivers/http/oauth2/oauth2.py
drb/exceptions/http.py
drb/topics/http/__init__.py
drb/topics/http/cortex.yml
drb_driver_http-1.3.7.dist-info/LICENCE.txt
drb_driver_http-1.3.7.dist-info/METADATA
drb_driver_http-1.3.7.dist-info/WHEEL
drb_driver_http-1.3.7.dist-info/entry_points.txt
drb_driver_http-1.3.7.dist-info/top_level.txt
drb_driver_http-1.3.7.dist-info/RECORD
