Metadata-Version: 2.1
Name: drb-driver-http
Version: 1.3.7
Summary: DRB Http driver
Author: GAEL Systems
Author-email: drb-python@gael.fr
License: LGPLv3
Project-URL: Documentation, http://drb-python.gitlab.io/impl/http
Project-URL: Source, https://gitlab.com/drb-python/impl/http
Classifier: Programming Language :: Python :: 3.8
Classifier: Environment :: Plugins
Classifier: License :: OSI Approved :: GNU Lesser General Public License v3 (LGPLv3)
Requires-Python: >=3.8
License-File: LICENCE.txt
Requires-Dist: drb ~=2.2.0
Requires-Dist: tenacity <8.3.0,>=8.0.1
